[{"plays": "23", "name": "Sikth"}, {"plays": "23", "name": "Structures"}, {"plays": "22", "name": "Peace"}, {"plays": "17", "name": "Biffy Clyro"}, {"plays": "13", "name": "Childish Gambino"}, {"plays": "11", "name": "Alexisonfire"}, {"plays": "10", "name": "Coldplay"}, {"plays": "10", "name": "Architects"}, {"plays": "9", "name": "Bombay Bicycle Club"}, {"plays": "8", "name": "Animals as Leaders"}, {"plays": "7", "name": "Sithu Aye"}, {"plays": "6", "name": "Cold War Kids"}, {"plays": "6", "name": "Stations"}, {"plays": "6", "name": "Alt-J"}, {"plays": "5", "name": "Deftones"}, {"plays": "3", "name": "Volumes"}, {"plays": "2", "name": "And So I Watch You From Afar"}, {"plays": "1", "name": "blink-182"}, {"plays": "1", "name": "Midlake"}, {"plays": "1", "name": "The Neighbourhood"}]